resetpassword
tests
