Metadata-Version: 2.1
Name: tgapp-resetpassword
Version: 0.2.7
Summary: Pluggable application for TurboGears2 that permits to change user password or reset it when lost, with sqla and ming compatibility
Home-page: https://github.com/axant/tgapp-resetpassword
Author: Simone Gasbarroni
Author-email: simone.gasbarroni@gmail.com
License: MIT
Keywords: turbogears2.application
Platform: UNKNOWN
Provides-Extra: testing
